draugr/README.md
draugr/__init__.py
draugr/airflow_utilities/__init__.py
draugr/airflow_utilities/enums.py
draugr/dlib_utilities/README.md
draugr/dlib_utilities/__init__.py
draugr/dlib_utilities/dlib_utilities.py
draugr/dlib_utilities/facealigner.py
draugr/drawers/README.md
draugr/drawers/__init__.py
draugr/drawers/drawer.py
draugr/drawers/mpl_drawers/README.md
draugr/drawers/mpl_drawers/__init__.py
draugr/drawers/mpl_drawers/discrete_scroll_plot.py
draugr/drawers/mpl_drawers/distribution_plot.py
draugr/drawers/mpl_drawers/image_stream_plot.py
draugr/drawers/mpl_drawers/mpldrawer.py
draugr/drawers/mpl_drawers/series_scroll_plot.py
draugr/drawers/mpl_drawers/spectral/README.md
draugr/drawers/mpl_drawers/spectral/__init__.py
draugr/drawers/mpl_drawers/spectral/fast_fourier_transform.py
draugr/drawers/mpl_drawers/spectral/fast_fourier_transform_spectrogram.py
draugr/drawers/opencv_drawers/README.md
draugr/drawers/opencv_drawers/__init__.py
draugr/drawers/opencv_drawers/opencv_image_stream.py
draugr/drawers/terminal/README.md
draugr/drawers/terminal/__init__.py
draugr/drawers/terminal/terminal_image_renderer.py
draugr/drawers/terminal/terminal_plot.py
draugr/drawers/terminal/terminal_plotter.py
draugr/drawers/terminal/terminal_utilities.py
draugr/entry_points/README.md
draugr/entry_points/__init__.py
draugr/entry_points/cpu_usage_entry_point.py
draugr/entry_points/tensorboard_entry_point.py
draugr/entry_points/toggle_darkmode.py
draugr/entry_points/visdom_entry_point.py
draugr/extensions/README.md
draugr/extensions/__init__.py
draugr/extensions/skimage_utilities.py
draugr/extensions/sorcery_utilities.py
draugr/ffmpeg_utilities/README.md
draugr/ffmpeg_utilities/__init__.py
draugr/ffmpeg_utilities/extract.py
draugr/ffmpeg_utilities/merge.py
draugr/ffmpeg_utilities/sequencify.py
draugr/ffmpeg_utilities/split.py
draugr/matlab_utilities/README.md
draugr/matlab_utilities/__init__.py
draugr/matlab_utilities/conversion.py
draugr/matlab_utilities/matlab_conversion_utilities.py
Draugr-1.2.1.dist-info/LICENSE.md
Draugr-1.2.1.dist-info/METADATA
Draugr-1.2.1.dist-info/WHEEL
Draugr-1.2.1.dist-info/entry_points.txt
Draugr-1.2.1.dist-info/top_level.txt
Draugr-1.2.1.dist-info/RECORD
