Metadata-Version: 2.1
Name: Draugr
Version: 1.2.1
Summary: A package for plotting directly in your terminal
Home-page: https://github.com/pything/draugr
Download-URL: https://github.com/pything/draugr/releases
Author: Christian Heider Lindbjerg
Author-email: christian.heider@alexandra.dk
Maintainer: Christian Heider Lindbjerg
Maintainer-email: christian.heider@alexandra.dk
License: Apache License, Version 2.0
Keywords: python interface api
Classifier: Development Status :: 4 - Beta
Classifier: Environment :: Console
Classifier: Intended Audience :: End Users/Desktop
Classifier: Intended Audience :: Developers
Classifier: License :: OSI Approved :: Apache Software License
Classifier: Operating System :: MacOS :: MacOS X
Classifier: Operating System :: Microsoft :: Windows
Classifier: Operating System :: POSIX
Classifier: Operating System :: OS Independent
Classifier: Programming Language :: Python :: 3
Classifier: Natural Language :: English
Requires-Python: >=3.6
License-File: LICENSE.md
Requires-Dist: apppath>=1.0.5
Requires-Dist: six
Requires-Dist: wrapt
Requires-Dist: numpy>=1.20.0
Requires-Dist: warg>=1.3.2
Requires-Dist: psutil
Provides-Extra: all
Requires-Dist: pytest>=4.4.1; extra == "all"
Requires-Dist: pygame; extra == "all"
Requires-Dist: scikit-learn; extra == "all"
Requires-Dist: matplotlib; extra == "all"
Requires-Dist: twine>=4.0.1; extra == "all"
Requires-Dist: sorcery; extra == "all"
Requires-Dist: cloudpickle; extra == "all"
Requires-Dist: wrapt; extra == "all"
Requires-Dist: torchvision>=0.13.0; extra == "all"
Requires-Dist: torch>=1.12.0; extra == "all"
Requires-Dist: pyperf>=2.3.1; extra == "all"
Requires-Dist: types-six>=1.1.1; extra == "all"
Requires-Dist: draugr; extra == "all"
Requires-Dist: visdom; extra == "all"
Requires-Dist: tqdm; extra == "all"
Requires-Dist: pip>=22.1.2; extra == "all"
Requires-Dist: isort>=5.10.1; extra == "all"
Requires-Dist: coveralls>=3.3.1; extra == "all"
Requires-Dist: pandas>=2.1.1; extra == "all"
Requires-Dist: pytest-runner; extra == "all"
Requires-Dist: tensorboard; extra == "all"
Requires-Dist: pandas; extra == "all"
Requires-Dist: apppath; extra == "all"
Requires-Dist: seaborn>=0.13.0; extra == "all"
Requires-Dist: wheel>=0.37.1; extra == "all"
Requires-Dist: six; extra == "all"
Requires-Dist: pynput; extra == "all"
Requires-Dist: notus; extra == "all"
Requires-Dist: numpy>=1.20.0; extra == "all"
Requires-Dist: tox>=3.25.0; extra == "all"
Requires-Dist: psutil; extra == "all"
Requires-Dist: doc8>=0.11.2; extra == "all"
Requires-Dist: apppath>=1.0.5; extra == "all"
Requires-Dist: scikit-learn>=1.3.1; extra == "all"
Requires-Dist: torch; extra == "all"
Requires-Dist: warg; extra == "all"
Requires-Dist: numpy; extra == "all"
Requires-Dist: matplotlib>=3.5.2; extra == "all"
Requires-Dist: pathos; extra == "all"
Requires-Dist: scipy>=1.11.3; extra == "all"
Requires-Dist: black>=22.3.0; extra == "all"
Requires-Dist: pylint; extra == "all"
Requires-Dist: sphinxcontrib-programoutput; extra == "all"
Requires-Dist: pytest-cov>=3.0.0; extra == "all"
Requires-Dist: numpy>=1.26.0; extra == "all"
Requires-Dist: mock; extra == "all"
Requires-Dist: pydocstyle; extra == "all"
Requires-Dist: pycodestyle>=2.8.0; extra == "all"
Requires-Dist: sh; extra == "all"
Requires-Dist: pre-commit>=2.19.0; extra == "all"
Requires-Dist: bandit>=1.7.7; extra == "all"
Requires-Dist: matplotlib>=3.8.1; extra == "all"
Requires-Dist: opencv-python; extra == "all"
Requires-Dist: flake8>=4.0.1; extra == "all"
Requires-Dist: warg>=1.3.2; extra == "all"
Requires-Dist: pytest>=7.1.2; extra == "all"
Provides-Extra: dev
Requires-Dist: pytest>=4.4.1; extra == "dev"
Requires-Dist: pygame; extra == "dev"
Requires-Dist: scikit-learn; extra == "dev"
Requires-Dist: matplotlib; extra == "dev"
Requires-Dist: twine>=4.0.1; extra == "dev"
Requires-Dist: sorcery; extra == "dev"
Requires-Dist: cloudpickle; extra == "dev"
Requires-Dist: wrapt; extra == "dev"
Requires-Dist: torchvision>=0.13.0; extra == "dev"
Requires-Dist: torch>=1.12.0; extra == "dev"
Requires-Dist: pyperf>=2.3.1; extra == "dev"
Requires-Dist: types-six>=1.1.1; extra == "dev"
Requires-Dist: tqdm; extra == "dev"
Requires-Dist: visdom; extra == "dev"
Requires-Dist: pip>=22.1.2; extra == "dev"
Requires-Dist: isort>=5.10.1; extra == "dev"
Requires-Dist: coveralls>=3.3.1; extra == "dev"
Requires-Dist: pandas>=2.1.1; extra == "dev"
Requires-Dist: pytest-runner; extra == "dev"
Requires-Dist: tensorboard; extra == "dev"
Requires-Dist: pandas; extra == "dev"
Requires-Dist: apppath; extra == "dev"
Requires-Dist: seaborn>=0.13.0; extra == "dev"
Requires-Dist: wheel>=0.37.1; extra == "dev"
Requires-Dist: six; extra == "dev"
Requires-Dist: pynput; extra == "dev"
Requires-Dist: notus; extra == "dev"
Requires-Dist: numpy>=1.20.0; extra == "dev"
Requires-Dist: warg>=1.3.2; extra == "dev"
Requires-Dist: tox>=3.25.0; extra == "dev"
Requires-Dist: psutil; extra == "dev"
Requires-Dist: doc8>=0.11.2; extra == "dev"
Requires-Dist: apppath>=1.0.5; extra == "dev"
Requires-Dist: scikit-learn>=1.3.1; extra == "dev"
Requires-Dist: torch; extra == "dev"
Requires-Dist: warg; extra == "dev"
Requires-Dist: numpy; extra == "dev"
Requires-Dist: matplotlib>=3.5.2; extra == "dev"
Requires-Dist: pathos; extra == "dev"
Requires-Dist: scipy>=1.11.3; extra == "dev"
Requires-Dist: black>=22.3.0; extra == "dev"
Requires-Dist: pylint; extra == "dev"
Requires-Dist: sphinxcontrib-programoutput; extra == "dev"
Requires-Dist: pytest-cov>=3.0.0; extra == "dev"
Requires-Dist: numpy>=1.26.0; extra == "dev"
Requires-Dist: mock; extra == "dev"
Requires-Dist: pydocstyle; extra == "dev"
Requires-Dist: pycodestyle>=2.8.0; extra == "dev"
Requires-Dist: sh; extra == "dev"
Requires-Dist: pre-commit>=2.19.0; extra == "dev"
Requires-Dist: bandit>=1.7.7; extra == "dev"
Requires-Dist: matplotlib>=3.8.1; extra == "dev"
Requires-Dist: opencv-python; extra == "dev"
Requires-Dist: flake8>=4.0.1; extra == "dev"
Requires-Dist: draugr; extra == "dev"
Requires-Dist: pytest>=7.1.2; extra == "dev"
Provides-Extra: dlib
Requires-Dist: opencv-python; extra == "dlib"
Provides-Extra: docs
Requires-Dist: warg; extra == "docs"
Requires-Dist: apppath; extra == "docs"
Requires-Dist: sphinxcontrib-programoutput; extra == "docs"
Requires-Dist: draugr; extra == "docs"
Provides-Extra: drawers
Requires-Dist: torch; extra == "drawers"
Requires-Dist: scikit-learn; extra == "drawers"
Requires-Dist: matplotlib; extra == "drawers"
Requires-Dist: pynput; extra == "drawers"
Requires-Dist: notus; extra == "drawers"
Provides-Extra: extensions
Requires-Dist: sorcery; extra == "extensions"
Provides-Extra: ja
Requires-Dist: tensorboard; extra == "ja"
Provides-Extra: linu
Requires-Dist: psutil; extra == "linu"
Requires-Dist: sh; extra == "linu"
Provides-Extra: multiprocessing
Requires-Dist: cloudpickle; extra == "multiprocessing"
Provides-Extra: opencv
Requires-Dist: opencv-python; extra == "opencv"
Provides-Extra: progress_bars
Requires-Dist: notus; extra == "progress-bars"
Requires-Dist: pathos; extra == "progress-bars"
Provides-Extra: pygame
Requires-Dist: pygame; extra == "pygame"
Provides-Extra: setup
Requires-Dist: tqdm; extra == "setup"
Requires-Dist: pytest-runner; extra == "setup"
Provides-Extra: tests
Requires-Dist: mock; extra == "tests"
Requires-Dist: pytest>=4.4.1; extra == "tests"
Provides-Extra: torch
Requires-Dist: matplotlib>=3.5.2; extra == "torch"
Requires-Dist: tensorboard; extra == "torch"
Requires-Dist: torchvision>=0.13.0; extra == "torch"
Requires-Dist: opencv-python; extra == "torch"
Requires-Dist: torch>=1.12.0; extra == "torch"
Provides-Extra: tqdm
Requires-Dist: tqdm; extra == "tqdm"
Requires-Dist: pathos; extra == "tqdm"
Provides-Extra: visualisation
Requires-Dist: numpy>=1.26.0; extra == "visualisation"
Requires-Dist: scikit-learn>=1.3.1; extra == "visualisation"
Requires-Dist: pandas>=2.1.1; extra == "visualisation"
Requires-Dist: seaborn>=0.13.0; extra == "visualisation"
Requires-Dist: scipy>=1.11.3; extra == "visualisation"
Requires-Dist: matplotlib>=3.8.1; extra == "visualisation"
Provides-Extra: windows
Requires-Dist: psutil; extra == "windows"
Provides-Extra: writers
Requires-Dist: numpy; extra == "writers"
Requires-Dist: scikit-learn; extra == "writers"
Requires-Dist: pandas; extra == "writers"
Requires-Dist: matplotlib; extra == "writers"
Requires-Dist: sorcery; extra == "writers"
Requires-Dist: visdom; extra == "writers"
